[
  {
    "type": "mod_tileset",
    "compatibility": ["UNDEAD_PEOPLE_BASE", "UNDEAD_PEOPLE", "MshockXottoplus", "UNDEAD_PEOPLE_LIGHT", "MSX++DEAD_PEOPLE" ],
    "tiles-new": [
      {
        "file": "./tiles/vehicle.png",
        "sprite_width":32,
        "sprite_height":32,
        "sprite_offset_x":0,
        "sprite_offset_y":0,      
        "tiles": [
          { "id": "vp_hdboardCrusader_hatch_wheel_left", "fg": 20, "rotates": true, "multitile": true },
          { "id": "vp_hdboardCrusader_hatch_wheel_right", "fg": 24, "rotates": true, "multitile": true }
        ]
      }
    ]
  }
]